pirat/__init__.py
pirat/__main__.py
pirat/_version.py
pirat/start.py
pirat/clustering_functions/__init__.py
pirat/clustering_functions/clustering.py
pirat/clustering_functions/data_preparation.py
pirat/clustering_functions/parameters.py
pirat/configuration_functions/__init__.py
pirat/configuration_functions/configuration.py
pirat/configuration_functions/file_operations.py
pirat/configuration_functions/post_processing.py
pirat/configuration_functions/reports_generation.py
pirat/configuration_functions/user_input.py
pirat/ping_pong/__init__.py
pirat/ping_pong/ping_pong_all.py
pirat/statistics_functions/__init__.py
pirat/statistics_functions/statistics.py
pirat-0.1.1.dist-info/licenses/LICENSE
pirat-0.1.1.dist-info/licenses/LICENSE:Zone.Identifier
pirat-0.1.1.dist-info/METADATA
pirat-0.1.1.dist-info/WHEEL
pirat-0.1.1.dist-info/entry_points.txt
pirat-0.1.1.dist-info/top_level.txt
pirat-0.1.1.dist-info/RECORD
