Metadata-Version: 2.4
Name: pirat
Version: 0.1.1
Summary: Package allowing to annotate piRNAs clusters from RNA-seq datafiles
Home-page: https://github.com/ylla-lab/piRAT
Author: Dominik Robak
Author-email: dominikrobak03@gmail.com
Classifier: Development Status :: 1 - Planning
Classifier: Intended Audience :: Science/Research
Classifier: License :: OSI Approved :: MIT License
Classifier: Operating System :: POSIX :: Linux
Classifier: Programming Language :: Python :: 3
Classifier: Programming Language :: Python :: 3.8
Classifier: Programming Language :: Python :: 3.9
Classifier: Programming Language :: Python :: 3.10
Classifier: Programming Language :: Python :: 3.11
Classifier: Programming Language :: Python :: 3.12
Requires-Python: >=3.8
License-File: LICENSE
License-File: LICENSE:Zone.Identifier
Requires-Dist: pysam>=0.22.0
Requires-Dist: numpy>=1.20.0
Requires-Dist: pandas>=2.0.0
Requires-Dist: kneed>=0.8.0
Requires-Dist: biopython>=1.80
Requires-Dist: tqdm>=4.60.0
Requires-Dist: PyPDF2>=3.0.0
Requires-Dist: tabulate>=0.9.0
Requires-Dist: seqlogo>=5.29.9
Requires-Dist: logomaker>=0.8
Requires-Dist: cairosvg>=2.7.0
Requires-Dist: matplotlib>=3.5.0
Requires-Dist: imgkit>=1.2.0
Requires-Dist: scipy>=1.10.0
Requires-Dist: matplotlib-venn>=1.1.0
Requires-Dist: seaborn>=0.13.0
Requires-Dist: intervaltree>=3.1.0
Requires-Dist: pyranges>=0.1.0
Requires-Dist: cycler>=0.12.0
Dynamic: author
Dynamic: author-email
Dynamic: classifier
Dynamic: home-page
Dynamic: license-file
Dynamic: requires-dist
Dynamic: requires-python
Dynamic: summary
